asolytics/__init__.py
asolytics/asolytics.py
asolytics/extract.py
asolytics/local.py
asolytics/reviews.py
asolytics/similar.py
asolytics/tags.py
asolytics/tracker.py
asolytics-1.3.1.dist-info/LICENSE.txt
asolytics-1.3.1.dist-info/METADATA
asolytics-1.3.1.dist-info/WHEEL
asolytics-1.3.1.dist-info/dependency_links.txt
asolytics-1.3.1.dist-info/entry_points.txt
asolytics-1.3.1.dist-info/top_level.txt
asolytics-1.3.1.dist-info/RECORD
