Metadata-Version: 2.1
Name: asolytics
Version: 1.3.1
Summary: ASO automation software tool on Google Play. Trend analysis, keyword popularity analysis and evaluation, competitor app analysis and keyword parsing.
Home-page: https://github.com/AsolyticsOpenSource/asolytics
Download-URL: https://github.com/AsolyticsOpenSource/asolytics/archive/refs/tags/aso.zip
Author: Asolytics Open Source
Author-email: asolytics@gmail.com
License: MIT
Keywords: ASO tools,Google Play,app store optimization,ASO intelligence,app ranking,app market analysis,mobile apps marketing
Classifier: License :: OSI Approved :: MIT License
Classifier: Programming Language :: Python :: 2.7
Classifier: Programming Language :: Python :: 3
Classifier: Programming Language :: Python :: 3.7
Requires-Python: >=3.7
License-File: LICENSE.txt
Requires-Dist: async-generator (==1.10)
Requires-Dist: attrs (==22.2.0)
Requires-Dist: certifi (==2022.12.7)
Requires-Dist: charset-normalizer (==2.1.1)
Requires-Dist: click (==8.1.3)
Requires-Dist: colorama (==0.4.6)
Requires-Dist: exceptiongroup (==1.1.0)
Requires-Dist: h11 (==0.14.0)
Requires-Dist: idna (==3.4)
Requires-Dist: importlib-metadata (==6.0.0)
Requires-Dist: jellyfish (==0.9.0)
Requires-Dist: networkx (==2.6.3)
Requires-Dist: numpy (==1.24.1)
Requires-Dist: outcome (==1.2.0)
Requires-Dist: packaging (==22.0)
Requires-Dist: prettytable (==3.5.0)
Requires-Dist: PySocks (==1.7.1)
Requires-Dist: python-dotenv (==0.21.0)
Requires-Dist: regex (==2022.10.31)
Requires-Dist: requests (==2.28.1)
Requires-Dist: segtok (==1.5.11)
Requires-Dist: selenium (==4.7.2)
Requires-Dist: sniffio (==1.3.0)
Requires-Dist: sortedcontainers (==2.4.0)
Requires-Dist: tabulate (==0.9.0)
Requires-Dist: tqdm (==4.64.1)
Requires-Dist: trio (==0.22.0)
Requires-Dist: trio-websocket (==0.9.2)
Requires-Dist: typing-extensions (==4.4.0)
Requires-Dist: urllib3 (==1.26.13)
Requires-Dist: wcwidth (==0.2.5)
Requires-Dist: webdriver-manager (==3.8.5)
Requires-Dist: wsproto (==1.2.0)
Requires-Dist: yake (==0.4.8)
Requires-Dist: zipp (==3.11.0)
Requires-Dist: langdetect (==1.0.9)
